pyhlo/__init__.py
pyhlo/hello.py
pyhlo-1.0.0.dist-info/LICENSE
pyhlo-1.0.0.dist-info/METADATA
pyhlo-1.0.0.dist-info/WHEEL
pyhlo-1.0.0.dist-info/entry_points.txt
pyhlo-1.0.0.dist-info/top_level.txt
pyhlo-1.0.0.dist-info/RECORD
