Metadata-Version: 2.1
Name: pyhlo
Version: 1.0.0
Summary: A Hello Program.
Author-email: Pankaj Jackson <pankajackson@live.co.uk>
Maintainer-email: Pankaj Jackson <pankajackson@live.co.uk>
License: GNU GENERAL PUBLIC LICENSE
Project-URL: Homepage, https://github.com/pankajackson/pyhlo
Project-URL: Bug Tracker, https://github.com/pankajackson/pyhlo/issues
Project-URL: Say Thanks!, https://www.evega.co.in
Project-URL: Source, https://github.com/pankajackson/pyhlo
Keywords: python,hello
Classifier: Programming Language :: Python :: 3
Classifier: Development Status :: 1 - Planning
Classifier: Intended Audience :: Developers
Classifier: License :: OSI Approved :: MIT License
Classifier: Operating System :: Unix
Classifier: Operating System :: MacOS :: MacOS X
Classifier: Operating System :: Microsoft :: Windows
Requires-Python: >=3.7
License-File: LICENSE
Requires-Dist: requests
